CHANGELOG.md
LICENSE
README.md
micropy/__init__.py
micropy/__main__.py
micropy/app/__init__.py
micropy/app/main.py
micropy/app/stubs.py
micropy/config/__init__.py
micropy/config/config.py
micropy/config/config_dict.py
micropy/config/config_json.py
micropy/config/config_source.py
micropy/data/__init__.py
micropy/data/schemas/firmware.json
micropy/data/schemas/stubs.json
micropy/data/sources.json
micropy/exceptions.py
micropy/logger.py
micropy/main.py
micropy/packages/__init__.py
micropy/packages/package.py
micropy/packages/source.py
micropy/packages/source_package.py
micropy/packages/source_path.py
micropy/project/__init__.py
micropy/project/checks.py
micropy/project/modules/__init__.py
micropy/project/modules/modules.py
micropy/project/modules/packages.py
micropy/project/modules/stubs.py
micropy/project/modules/templates.py
micropy/project/project.py
micropy/project/template/.gitignore
micropy/project/template/.pylintrc
micropy/project/template/.vscode/extensions.json
micropy/project/template/.vscode/settings.json
micropy/project/template/pymakr.conf
micropy/project/template/src/boot.py
micropy/project/template/src/main.py
micropy/project/template.py
micropy/py.typed
micropy/pyd/__init__.py
micropy/pyd/abc.py
micropy/pyd/backend_rshell.py
micropy/pyd/backend_upydevice.py
micropy/pyd/consumers.py
micropy/pyd/pydevice.py
micropy/stubs/__init__.py
micropy/stubs/manifest.py
micropy/stubs/package.py
micropy/stubs/repo.py
micropy/stubs/repo_package.py
micropy/stubs/repositories/__init__.py
micropy/stubs/repositories/micropy.py
micropy/stubs/repositories/micropython.py
micropy/stubs/repository_info.py
micropy/stubs/source.py
micropy/stubs/stubs.py
micropy/utils/__init__.py
micropy/utils/_compat.py
micropy/utils/decorators.py
micropy/utils/helpers.py
micropy/utils/stub.py
micropy/utils/types.py
micropy/utils/validate.py
micropy_cli-4.2.2.dist-info/LICENSE
micropy_cli-4.2.2.dist-info/METADATA
micropy_cli-4.2.2.dist-info/WHEEL
micropy_cli-4.2.2.dist-info/entry_points.txt
micropy_cli-4.2.2.dist-info/RECORD
