Metadata-Version: 2.1
Name: micropy-cli
Version: 4.2.2
Summary: Micropython Project Management Tool with VSCode support, Linting, Intellisense, Dependency Management, and more!
Home-page: https://github.com/BradenM/micropy-cli
License: MIT
Keywords: micropython,stubs,linting,vscode,intellisense
Author: Braden Mars
Author-email: bradenmars@bradenmars.me
Requires-Python: >=3.8,<3.12
Classifier: Development Status :: 5 - Production/Stable
Classifier: Intended Audience :: Developers
Classifier: License :: OSI Approved :: MIT License
Classifier: Operating System :: OS Independent
Classifier: Programming Language :: Python :: 3
Classifier: Programming Language :: Python :: 3.8
Classifier: Programming Language :: Python :: 3.9
Classifier: Programming Language :: Python :: 3.10
Classifier: Programming Language :: Python :: 3.11
Classifier: Programming Language :: Python :: Implementation :: CPython
Classifier: Programming Language :: Python :: Implementation :: MicroPython
Classifier: Topic :: Software Development :: Build Tools
Classifier: Topic :: Software Development :: Code Generators
Classifier: Topic :: Software Development :: Embedded Systems
Requires-Dist: GitPython (==3.1.31)
Requires-Dist: Jinja2 (==3.1.2)
Requires-Dist: MarkupSafe (==2.1.3)
Requires-Dist: attrs (==23.1.0)
Requires-Dist: boltons (==23.0.0)
Requires-Dist: cachier (==2.0.0)
Requires-Dist: click (==8.1.3)
Requires-Dist: colorama (==0.4.6) ; sys_platform == "win32"
Requires-Dist: distlib (==0.3.6)
Requires-Dist: dpath (==1.5.0)
Requires-Dist: importlib-metadata (==5.2.0) ; python_version < "3.10"
Requires-Dist: jsonschema (==3.2.0)
Requires-Dist: libcst (==0.4.10)
Requires-Dist: micropython-stubber (==1.13.7)
Requires-Dist: mypy (==1.2.0)
Requires-Dist: packaging (==21.3)
Requires-Dist: pydantic (==1.10.9)
Requires-Dist: python-minifier (==2.9.0)
Requires-Dist: questionary (==1.10.0)
Requires-Dist: requests (==2.31.0)
Requires-Dist: requirements-parser (==0.2.0)
Requires-Dist: rshell (>=0.0.31,<0.0.32) ; python_version < "3.10" and sys_platform == "win32"
Requires-Dist: rshell (>=0.0.31,<0.0.32) ; sys_platform != "win32"
Requires-Dist: tqdm (==4.65.0)
Requires-Dist: typer[all] (==0.9.0)
Requires-Dist: typing-extensions (==4.6.3)
Requires-Dist: upydevice (==0.3.8)
Project-URL: Documentation, https://micropy-cli.readthedocs.io
Project-URL: Repository, https://github.com/BradenM/micropy-cli
